template/__init__.py
template/models.py
template/template.py
utest/__init__.py
pyxingapi-0.0.0.dist-info/LICENSE
pyxingapi-0.0.0.dist-info/METADATA
pyxingapi-0.0.0.dist-info/WHEEL
pyxingapi-0.0.0.dist-info/top_level.txt
pyxingapi-0.0.0.dist-info/RECORD
