Metadata-Version: 2.1
Name: pyxingapi
Version: 0.0.0
Summary: Wrapper for eBEST xing API
Home-page: https://github.com/innovata/pyxingapi
Author: innovata sambong
Author-email: iinnovata@gmail.com
License: UNKNOWN
Platform: UNKNOWN
Classifier: Programming Language :: Python :: 3
Classifier: License :: OSI Approved :: MIT License
Classifier: Operating System :: OS Independent
Requires-Python: >=3.7
